opencopilot_db/__init__.py
opencopilot_db/chat_history.py
opencopilot_db/chatbot.py
opencopilot_db/chatbot_setting.py
opencopilot_db/database_setup.py
opencopilot_db/get_declarative_base.py
opencopilot_db/pdf_data_source_model.py
opencopilot_db/website_data_source.py
opencopilot_db-5.0.0.dist-info/METADATA
opencopilot_db-5.0.0.dist-info/WHEEL
opencopilot_db-5.0.0.dist-info/top_level.txt
opencopilot_db-5.0.0.dist-info/RECORD
