Metadata-Version: 2.1
Name: opencopilot-db
Version: 5.0.0
Summary: Database schemas for OpenCopilot microservices and plugins
Requires-Dist: sqlalchemy
Requires-Dist: pymysql
